CHANGELOG.md
quantum_linear_systems/__init__.py
quantum_linear_systems/compare_classiq_qiskit.py
quantum_linear_systems/execution/__init__.py
quantum_linear_systems/execution/aws_execution.py
quantum_linear_systems/execution/aws_requirements.txt
quantum_linear_systems/execution/naive_vqls_hybrid_task.py
quantum_linear_systems/implementations/__init__.py
quantum_linear_systems/implementations/hhl_classiq_implementation.py
quantum_linear_systems/implementations/hhl_qiskit_implementation.py
quantum_linear_systems/implementations/vqls_qiskit_implementation.py
quantum_linear_systems/plotting.py
quantum_linear_systems/quantum_linear_solver.py
quantum_linear_systems/toymodels.py
quantum_linear_systems/utils.py
quantum_linear_systems-0.1.0.dist-info/LICENSE
quantum_linear_systems-0.1.0.dist-info/METADATA
quantum_linear_systems-0.1.0.dist-info/WHEEL
quantum_linear_systems-0.1.0.dist-info/entry_points.txt
quantum_linear_systems-0.1.0.dist-info/RECORD
