Metadata-Version: 2.1
Name: quantum-linear-systems
Version: 0.1.0
Summary: Quantum algorithms to solve linear systems of equations.
Home-page: https://github.com/SURFQuantum/qc-quantum-linear-systems
License: Apache-2.0
Keywords: science,quantum
Author: dmark04
Author-email: dmark04@web.de
Requires-Python: >=3.9,<3.12
Classifier: Development Status :: 4 - Beta
Classifier: License :: OSI Approved :: Apache Software License
Classifier: Operating System :: OS Independent
Classifier: Programming Language :: Python :: 3
Classifier: Programming Language :: Python :: 3.9
Classifier: Programming Language :: Python :: 3.10
Classifier: Programming Language :: Python :: 3.11
Classifier: Topic :: Scientific/Engineering
Requires-Dist: classiq (>=0.32.0,<0.33.0)
Requires-Dist: matplotlib (>=3.8.2,<4.0.0)
Requires-Dist: numpy (>=1.23.0)
Requires-Dist: qiskit (>=0.43.0,<0.45.0)
Requires-Dist: qiskit-algorithms (>=0.2.1,<0.3.0)
Requires-Dist: quantum-linear-solvers (>=0.1.1,<0.2.0)
Requires-Dist: vqls-prototype (>=0.2.0,<0.3.0)
Project-URL: Repository, https://github.com/SURFQuantum/qc-quantum-linear-systems
